gstomd/__init__.py
gstomd/__main__.py
gstomd/convert.py
gstomd/gdoc.py
gstomd/gfolder.py
gstomd/node.py
gstomd/utils.py
gstomd/test/__init__.py
gstomd/test/test_Folder.py
GsuiteToMd-1.3.0.dist-info/LICENSE
GsuiteToMd-1.3.0.dist-info/METADATA
GsuiteToMd-1.3.0.dist-info/WHEEL
GsuiteToMd-1.3.0.dist-info/top_level.txt
GsuiteToMd-1.3.0.dist-info/RECORD
